pythils/__init__.py
pythils/config.py
pythils/interface.py
pythils/placeholder.py
pythils-0.1.1.dist-info/METADATA
pythils-0.1.1.dist-info/WHEEL
pythils-0.1.1.dist-info/top_level.txt
pythils-0.1.1.dist-info/RECORD
