Metadata-Version: 2.4
Name: pythils
Version: 0.1.1
Summary: A Python utilities package.
Requires-Python: >=3.8
Provides-Extra: toml
Requires-Dist: toml; extra == "toml"
Provides-Extra: dotenv
Requires-Dist: dotenv; extra == "dotenv"
Provides-Extra: yaml
Requires-Dist: pyyaml; extra == "yaml"
Provides-Extra: all
Requires-Dist: pyyaml; extra == "all"
Requires-Dist: toml; extra == "all"
Requires-Dist: dotenv; extra == "all"
